INEAPIpy/INE_Filtering.py
INEAPIpy/INE_URL_Treatment.py
INEAPIpy/INE_functions.py
INEAPIpy/Wrapper.py
INEAPIpy/__init__.py
INEAPIpy/Models/FunctionInputsModels.py
INEAPIpy/Models/INEModels.py
INEAPIpy/Models/URLModels.py
INEAPIpy/Models/__init__.py
INEAPIpy/urlrequestsmangement/src/RequestsManagement.py
INEAPIpy/urlrequestsmangement/src/__init__.py
INEAPIpy/urlrequestsmangement/tests/test1.py
INEAPIpy/urlrequestsmangement/tests/test2.py
INEAPIpy/urlrequestsmangement/tests/test_requests.py
ineapipy-0.1.4.dist-info/licenses/LICENSE.md
ineapipy-0.1.4.dist-info/METADATA
ineapipy-0.1.4.dist-info/WHEEL
ineapipy-0.1.4.dist-info/top_level.txt
ineapipy-0.1.4.dist-info/RECORD
