Metadata-Version: 2.4
Name: ineapipy
Version: 0.1.4
Summary: INE API Wrapper, provides classes to make requests to the INE API, both sync and async.
Author-email: VanceVisarisTenenbaum <144833048+VanceVisarisTenenbaum@users.noreply.github.com>
License-Expression: Apache-2.0
Project-URL: Repository, https://github.com/VanceVisarisTenenbaum/INEAPIpy
Project-URL: Issues, https://github.com/VanceVisarisTenenbaum/INEAPIpy/issues
Keywords: INE,Instituto,Nacional,API,Statistics,Estadisticas,Stats,INEAPI
Classifier: Programming Language :: Python :: 3
Classifier: Operating System :: OS Independent
Requires-Python: >=3.10
License-File: LICENSE.md
Requires-Dist: requests>=2.32.4
Requires-Dist: aiohttp>=3.12.14
Requires-Dist: yarl>=1.20.1
Requires-Dist: pydantic>=2.11.5
Dynamic: license-file
